quda/data/__init__.py
quda/data/loader.py
quda_data-0.1.1.dist-info/METADATA
quda_data-0.1.1.dist-info/WHEEL
quda_data-0.1.1.dist-info/top_level.txt
quda_data-0.1.1.dist-info/RECORD
