Metadata-Version: 2.4
Name: quda-data
Version: 0.1.1
License-Expression: MIT
Requires-Python: >=3.12
Requires-Dist: pandas>=2.3.0
Requires-Dist: polars>=1.31.0
Requires-Dist: quda>=1.0.0b0
Requires-Dist: scikit-learn>=1.7.0
Requires-Dist: xcals>=0.0.4
